pybirthday/__init__.py
pybirthday/__main__.py
pybirthday/pybirthday.py
pybirthday-0.1.1.dist-info/licenses/LICENSE
pybirthday-0.1.1.dist-info/METADATA
pybirthday-0.1.1.dist-info/WHEEL
pybirthday-0.1.1.dist-info/entry_points.txt
pybirthday-0.1.1.dist-info/top_level.txt
pybirthday-0.1.1.dist-info/RECORD
