Metadata-Version: 2.4
Name: pybirthday
Version: 0.1.1
Summary: A Python package that lets users generate festive birthday-themed visuals.
Author-email: Shuyuan Yang <sy3644@nyu.edu>, Frank Fang <hf2371@nyu.edu>, Lauren Zhou <llz3185@nyu.edu>, Eric Xu <zx1244@nyu.edu>
License:                     GNU GENERAL PUBLIC LICENSE
Project-URL: Homepage, https://github.com/software-students-spring2025/3-python-package-helloworld
Project-URL: Repository, https://github.com/software-students-spring2025/3-python-package-helloworld.git
Project-URL: Bug Tracker, https://github.com/software-students-spring2025/3-python-package-helloworld/issues
Keywords: python,package,build,tutorial
Classifier: Programming Language :: Python :: 3
Classifier: Intended Audience :: Education
Classifier: License :: OSI Approved :: GNU General Public License v3 (GPLv3)
Classifier: Operating System :: OS Independent
Requires-Python: >=3.7
License-File: LICENSE
Provides-Extra: dev
Requires-Dist: pytest; extra == "dev"
Dynamic: license-file
